setup.py
kflogs/__init__.py
kflogs.egg-info/PKG-INFO
kflogs.egg-info/SOURCES.txt
kflogs.egg-info/dependency_links.txt
kflogs.egg-info/requires.txt
kflogs.egg-info/top_level.txt