Metadata-Version: 1.1
Name: kflogs
Version: 0.1.0
Summary: Amazon Kinesis Firehose logging handler and utilities
Home-page: https://github.com/marcy-terui/kflogs
Author: Masashi Terui
Author-email: marcy9114+pypi@gmail.com
License: MIT License
Keywords: aws kinesis firehose logging
Platform: UNKNOWN
Classifier: Development Status :: 4 - Beta
Classifier: Intended Audience :: Developers
Classifier: License :: OSI Approved :: MIT License
Classifier: Programming Language :: Python
Classifier: Programming Language :: Python :: 2.7
Classifier: Programming Language :: Python :: 3
